datashelf/__init__.py
datashelf/datashelf.py
datashelf-0.1.0.dist-info/LICENSE
datashelf-0.1.0.dist-info/WHEEL
datashelf-0.1.0.dist-info/METADATA
datashelf-0.1.0.dist-info/RECORD
