Metadata-Version: 2.1
Name: datashelf
Version: 0.1.0
Summary: Convenient management of datasets
Home-page: https://github.com/datagazing/datashelf
Author: Brendan Strejcek
Author-email: brendan@datagazing.com
Requires-Python: >=3.7
Classifier: License :: OSI Approved :: MIT License
